Metadata-Version: 2.1
Name: prediction-flow-x
Version: 0.1.9
Summary: Deep-Learning based CTR models implemented by PyTorch
Home-page: https://github.com/jqsl2012/prediction-flow
Maintainer: jqsl202
Maintainer-email: jqsl202@163.com
License: MIT
Keywords: torch,ctr prediction,deep learning,deepfm,din,dnn,deep neural network
Platform: UNKNOWN
Classifier: Development Status :: 3 - Alpha
Classifier: License :: OSI Approved :: MIT License
Classifier: Operating System :: OS Independent
Classifier: Intended Audience :: Science/Research
Classifier: Intended Audience :: Developers
Classifier: Intended Audience :: Education
Classifier: Programming Language :: Python
Classifier: Programming Language :: Python :: 3
Classifier: Programming Language :: Python :: 3.6
Classifier: Topic :: Software Development
Classifier: Topic :: Scientific/Engineering
Requires-Python: >=3.6
License-File: LICENSE
Requires-Dist: numpy (>=1.16.0)
Requires-Dist: pandas (>=0.24.2)
Requires-Dist: torch (>=1.1.0)
Requires-Dist: tqdm (>=4.32.0)
Requires-Dist: scikit-learn (>=0.20.0)
